MANIFEST.in
README.md
setup.cfg
setup.py
h2sastscan-reports.egg-info/PKG-INFO
h2sastscan-reports.egg-info/SOURCES.txt
h2sastscan-reports.egg-info/dependency_links.txt
h2sastscan-reports.egg-info/requires.txt
h2sastscan-reports.egg-info/top_level.txt
reporter/__init__.py
reporter/grafeas.py
reporter/sarif.py
reporter/utils.py
reporter/templates/base.html
reporter/templates/dep-report.html
reporter/templates/sast-report.html
test/__init__.py
test/test_sarif.py